cpx_io/__init__.py
cpx_io/cli/__init__.py
cpx_io/cli/cli.py
cpx_io/cli/cpx_ap.py
cpx_io/cli/cpx_e.py
cpx_io/cpx_system/__init__.py
cpx_io/cpx_system/cpx_base.py
cpx_io/cpx_system/cpx_dataclasses.py
cpx_io/cpx_system/cpx_module.py
cpx_io/cpx_system/io_thread.py
cpx_io/cpx_system/cpx_ap/__init__.py
cpx_io/cpx_system/cpx_ap/ap_docu_generator.py
cpx_io/cpx_system/cpx_ap/ap_modbus_registers.py
cpx_io/cpx_system/cpx_ap/ap_module.py
cpx_io/cpx_system/cpx_ap/ap_parameter.py
cpx_io/cpx_system/cpx_ap/ap_product_categories.py
cpx_io/cpx_system/cpx_ap/ap_supported_datatypes.py
cpx_io/cpx_system/cpx_ap/ap_supported_functions.py
cpx_io/cpx_system/cpx_ap/cpx_ap.py
cpx_io/cpx_system/cpx_ap/builder/__init__.py
cpx_io/cpx_system/cpx_ap/builder/ap_module_builder.py
cpx_io/cpx_system/cpx_ap/builder/apdd_information_builder.py
cpx_io/cpx_system/cpx_ap/builder/channel_builder.py
cpx_io/cpx_system/cpx_ap/builder/diagnosis_builder.py
cpx_io/cpx_system/cpx_ap/builder/parameter_builder.py
cpx_io/cpx_system/cpx_ap/builder/physical_quantity_builder.py
cpx_io/cpx_system/cpx_ap/checker/apdd_checker.py
cpx_io/cpx_system/cpx_ap/dataclasses/__init__.py
cpx_io/cpx_system/cpx_ap/dataclasses/apdd_information.py
cpx_io/cpx_system/cpx_ap/dataclasses/channels.py
cpx_io/cpx_system/cpx_ap/dataclasses/module_diagnosis.py
cpx_io/cpx_system/cpx_ap/dataclasses/module_parameters.py
cpx_io/cpx_system/cpx_ap/dataclasses/system_parameters.py
cpx_io/cpx_system/cpx_e/__init__.py
cpx_io/cpx_system/cpx_e/cpx_e.py
cpx_io/cpx_system/cpx_e/cpx_e_enums.py
cpx_io/cpx_system/cpx_e/cpx_e_modbus_registers.py
cpx_io/cpx_system/cpx_e/cpx_e_module_definitions.py
cpx_io/cpx_system/cpx_e/cpx_e_supported_datatypes.py
cpx_io/cpx_system/cpx_e/e16di.py
cpx_io/cpx_system/cpx_e/e1ci.py
cpx_io/cpx_system/cpx_e/e4aiui.py
cpx_io/cpx_system/cpx_e/e4aoui.py
cpx_io/cpx_system/cpx_e/e4iol.py
cpx_io/cpx_system/cpx_e/e8do.py
cpx_io/cpx_system/cpx_e/eep.py
cpx_io/utils/__init__.py
cpx_io/utils/boollist.py
cpx_io/utils/helpers.py
festo_cpx_io-0.11.1.dist-info/licenses/LICENSE
festo_cpx_io-0.11.1.dist-info/METADATA
festo_cpx_io-0.11.1.dist-info/WHEEL
festo_cpx_io-0.11.1.dist-info/entry_points.txt
festo_cpx_io-0.11.1.dist-info/top_level.txt
festo_cpx_io-0.11.1.dist-info/RECORD
