Metadata-Version: 2.4
Name: festo-cpx-io
Version: 0.11.1
Summary: Library to control and access festo CPX modules
Author-email: Jan Hildenbrand <jan.hildenbrand@festo.com>, Martin Wiesner <martin.wiesner@festo.com>, Elias Rosch <elias.rosch@festo.com>
License: MIT
Project-URL: Homepage, https://github.com/Festo-se/festo-cpx-io
Project-URL: Documentation, https://festo-se.github.io/festo-cpx-io/
Project-URL: Repository, https://github.com/Festo-se/festo-cpx-io
Project-URL: Changelog, https://github.com/Festo-se/festo-cpx-io/blob/main/CHANGELOG.md
Classifier: Programming Language :: Python :: 3
Classifier: License :: OSI Approved :: MIT License
Classifier: Operating System :: OS Independent
Requires-Python: >=3.10
License-File: LICENSE
Requires-Dist: pymodbus==3.11.3
Requires-Dist: platformdirs>=4.5.0
Requires-Dist: requests>=2.32.5
Provides-Extra: cli
Requires-Dist: rich>=14.2.0; extra == "cli"
Dynamic: license-file
